dns/__init__.py
dns/_asyncbackend.py
dns/_asyncio_backend.py
dns/_ddr.py
dns/_features.py
dns/_immutable_ctx.py
dns/_no_ssl.py
dns/_tls_util.py
dns/_trio_backend.py
dns/asyncbackend.py
dns/asyncquery.py
dns/asyncresolver.py
dns/btree.py
dns/btreezone.py
dns/dnssec.py
dns/dnssectypes.py
dns/e164.py
dns/edns.py
dns/entropy.py
dns/enum.py
dns/exception.py
dns/flags.py
dns/grange.py
dns/immutable.py
dns/inet.py
dns/ipv4.py
dns/ipv6.py
dns/message.py
dns/name.py
dns/namedict.py
dns/nameserver.py
dns/node.py
dns/opcode.py
dns/py.typed
dns/query.py
dns/rcode.py
dns/rdata.py
dns/rdataclass.py
dns/rdataset.py
dns/rdatatype.py
dns/renderer.py
dns/resolver.py
dns/reversename.py
dns/rrset.py
dns/serial.py
dns/set.py
dns/tokenizer.py
dns/transaction.py
dns/tsig.py
dns/tsigkeyring.py
dns/ttl.py
dns/update.py
dns/version.py
dns/versioned.py
dns/win32util.py
dns/wire.py
dns/xfr.py
dns/zone.py
dns/zonefile.py
dns/zonetypes.py
dns/dnssecalgs/__init__.py
dns/dnssecalgs/base.py
dns/dnssecalgs/cryptography.py
dns/dnssecalgs/dsa.py
dns/dnssecalgs/ecdsa.py
dns/dnssecalgs/eddsa.py
dns/dnssecalgs/rsa.py
dns/quic/__init__.py
dns/quic/_asyncio.py
dns/quic/_common.py
dns/quic/_sync.py
dns/quic/_trio.py
dns/rdtypes/__init__.py
dns/rdtypes/dnskeybase.py
dns/rdtypes/dsbase.py
dns/rdtypes/euibase.py
dns/rdtypes/mxbase.py
dns/rdtypes/nsbase.py
dns/rdtypes/svcbbase.py
dns/rdtypes/tlsabase.py
dns/rdtypes/txtbase.py
dns/rdtypes/util.py
dns/rdtypes/ANY/AFSDB.py
dns/rdtypes/ANY/AMTRELAY.py
dns/rdtypes/ANY/AVC.py
dns/rdtypes/ANY/CAA.py
dns/rdtypes/ANY/CDNSKEY.py
dns/rdtypes/ANY/CDS.py
dns/rdtypes/ANY/CERT.py
dns/rdtypes/ANY/CNAME.py
dns/rdtypes/ANY/CSYNC.py
dns/rdtypes/ANY/DLV.py
dns/rdtypes/ANY/DNAME.py
dns/rdtypes/ANY/DNSKEY.py
dns/rdtypes/ANY/DS.py
dns/rdtypes/ANY/DSYNC.py
dns/rdtypes/ANY/EUI48.py
dns/rdtypes/ANY/EUI64.py
dns/rdtypes/ANY/GPOS.py
dns/rdtypes/ANY/HINFO.py
dns/rdtypes/ANY/HIP.py
dns/rdtypes/ANY/ISDN.py
dns/rdtypes/ANY/L32.py
dns/rdtypes/ANY/L64.py
dns/rdtypes/ANY/LOC.py
dnspython-2.8.0rc1.dist-info/METADATA
dnspython-2.8.0rc1.dist-info/WHEEL
dnspython-2.8.0rc1.dist-info/licenses/LICENSE
dnspython-2.8.0rc1.dist-info/RECORD
