Metadata-Version: 2.4
Name: dnspython
Version: 2.8.0rc1
Summary: DNS toolkit
Project-URL: homepage, https://www.dnspython.org
Project-URL: repository, https://github.com/rthalley/dnspython.git
Project-URL: documentation, https://dnspython.readthedocs.io/en/stable/
Project-URL: issues, https://github.com/rthalley/dnspython/issues
Author-email: Bob Halley <halley@dnspython.org>
License: ISC
License-File: LICENSE
Classifier: Development Status :: 5 - Production/Stable
Classifier: Intended Audience :: Developers
Classifier: Intended Audience :: System Administrators
Classifier: License :: OSI Approved :: ISC License (ISCL)
Classifier: Operating System :: Microsoft :: Windows
Classifier: Operating System :: POSIX
Classifier: Programming Language :: Python
Classifier: Programming Language :: Python :: 3
Classifier: Programming Language :: Python :: 3.10
Classifier: Programming Language :: Python :: 3.11
Classifier: Programming Language :: Python :: 3.12
Classifier: Programming Language :: Python :: 3.13
Classifier: Topic :: Internet :: Name Service (DNS)
Classifier: Topic :: Software Development :: Libraries :: Python Modules
Requires-Python: >=3.10
Provides-Extra: dev
Requires-Dist: black>=25.1.0; extra == 'dev'
Requires-Dist: coverage>=7.0; extra == 'dev'
Requires-Dist: flake8>=7; extra == 'dev'
Requires-Dist: hypercorn>=0.17.0; extra == 'dev'
Requires-Dist: mypy>=1.17; extra == 'dev'
Requires-Dist: pylint>=3; extra == 'dev'
Requires-Dist: pytest-cov>=6.2.0; extra == 'dev'
Requires-Dist: pytest>=8.4; extra == 'dev'
Requires-Dist: quart-trio>=0.12.0; extra == 'dev'
Requires-Dist: sphinx-rtd-theme>=3.0.0; extra == 'dev'
Requires-Dist: sphinx>=8.2.0; extra == 'dev'
Requires-Dist: twine>=6.1.0; extra == 'dev'
Requires-Dist: wheel>=0.45.0; extra == 'dev'
Provides-Extra: dnssec
Requires-Dist: cryptography>=45; extra == 'dnssec'
Provides-Extra: doh
Requires-Dist: h2>=4.2.0; extra == 'doh'
Requires-Dist: httpcore>=1.0.0; extra == 'doh'
Requires-Dist: httpx>=0.28.0; extra == 'doh'
Provides-Extra: doq
Requires-Dist: aioquic>=1.2.0; extra == 'doq'
Provides-Extra: idna
Requires-Dist: idna>=3.10; extra == 'idna'
Provides-Extra: trio
Requires-Dist: trio>=0.30; extra == 'trio'
Provides-Extra: wmi
Requires-Dist: wmi>=1.5.1; (platform_system == 'Windows') and extra == 'wmi'
